{
    "word": "точно",
    "shortening_pos": 0,
    "articles": [
        {
            "text": "<i>нареч.</i> 1. (<i>безошибочно</i>) kesen-kes; tamam; tam (<i>полностью</i>); doğru (<i>верно</i>); <b>~ сказать не могу</b> kesen-kes ayt<stress>a</stress>mayım; <b>причину мы пока ~ не знаем</b> sebebini<stress>a</stress>lâ daa tam b<stress>i</stress>lmeymiz; <b>я ~ не помню</b> tam hatırlap ol<stress>a</stress>mayım; <b>~ следовать приказам</b> emirlerge kesen-kes itaat etmek; <b>часы идут ~</b> saat doğru işley; <b>статья переведена ~</b> maqaleniñ tercimesi doğr<stress>u</stress>dır, maqale doğru tercime etildi; <b>~ подсчитать</b> doğru esap etmek; <b>точнее</b> daa doğrusı; 2. (<i>как раз, ровно</i>) t<stress>a</stress>mam, dos-doğru; <b>поезд прибыл ~ по расписанию</b> tren (<i>или</i> p<stress>o</stress>yezd) tamam vaqtında keldi; <b>~ так же</b> tamam öyle (de), tamam onıñ kibi (de); <b>~ в два часа</b> tamam saat ekide; <b>~ так, как ты хотел</b> tamam seniñ istegeniñ kibi",
            "accent_pos": null
        },
        {
            "text": "<i>союз</i> (<i>как, словно</i>) kibi, s<stress>a</stress>nki, g<stress>u</stress>ya,<stress>a</stress>ynı, tıpqı, -day (<i>диал. ст.</i>), dayın (<i>диал. ст.</i>); <b>он летит, ~ птица</b> о, bir quş kibi (<i>или</i> quşday) uça; <b>он кричал, ~ сумасшедший</b> deli kibi qıçıra edi; ",
            "accent_pos": null
        },
        {
            "text": "(<i>так, верно</i>) ebet, e (<i>разг.</i>), doğru; <b>~, это он сделал</b> ebet (<i>или</i> doğru), о bunı yaptı (<i>или</i> bunı yapqan<stress>o</stress>dır)",
            "accent_pos": null
        }
    ]
}