{
    "word": "доступность",
    "shortening_pos": 0,
    "articles": [
        {
            "text": "1. çıqa bilm<stress>e</stress>; <b>~ этих гор для любого альпиниста</b> bu dağlarğa er dağcınıñ çıqa bilmesi; 2. uyğun olm<stress>a</stress>; <b>~ местности для танков</b> yerniñ tank areketlerine uyğun olması; 3. kelişikli olm<stress>a</stress>; <b>~ цен</b> fiyatlarnıñ kelişikli olması; 4. alına bilm<stress>e</stress>; <b>~ этих товаров</b> bu mallarnıñ alına bilmesi; 5. qullana bilm<stress>e</stress>; <b>~ библиотек для каждого желающего</b> er istegenniñ kitaphanelerni qullana bilmesi; 6. añlayışlı olm<stress>a</stress>; <b>~ изложения</b> añlatuvnıñ añlayışlı olması",
            "accent_pos": null
        }
    ]
}