{
    "word": "необходимый",
    "shortening_pos": 9,
    "articles": [
        {
            "text": "1. kerekli, lâzim, lâzim olğan, zaruriy, vacip, lâbit, iqtiza, elzem, lüzümiy; <b>мне ~а твоя помощь</b> maña seniñ yardımıñ kerek; <b>быть ~ым кому-либо</b> birine kerek olmaq, icap etmek; <b>быть крайне ~ым</b> pek (<i>или</i> ğayet) kerek olmaq; farz olmaq (<i>рел.</i>); <b>~ые книги</b> kerekli kitaplar; 2. kerekli, zarur olğan; <b>создать ~ые условия</b> kerekli şarait yaratmaq; <b>он сделал ~ые выводы</b> о, kerekli hulâsalar çıqardı",
            "accent_pos": null
        }
    ]
}