{
    "word": "удовольствие",
    "shortening_pos": 11,
    "articles": [
        {
            "text": "zevq (-qı), sefa, keyf, haz (<i>наслаждение</i>); memnüniyet, memnünlik, hoşnutlıq (<i>чувство приятности, радости</i>); <b>испытывать ~е от чего-либо</b> bir şeyden zevq (<i>или</i> haz) duymaq, bir şeyden sefa (<i>или</i> zevq-sefa) sürmek; <b>получать ~е от чего-либо</b> bir şeyden zevq almaq (<i>или</i> haz etmek, keyflenmek); <b>доставлять ~е кому-либо</b> birine zevq bermek; <b>мы не намерены доставлять ему такое ~е</b> oña bu zevqnı bermek niyetinde deg<stress>i</stress>lmiz; <b>это не даёт никакого ~я</b> bunıñ iç tadı (<i>или</i> zevqı)<stress>o</stress>lmay; <b>он ловит рыбу ради ~я</b> zevq içün balıq tutar; <b>с ~ем!</b> memnüniy<stress>e</stress>tnen!; <b>мы с ~ем слушали её рассказы</b> biz onıñ ikâyelerini memnüniy<stress>e</stress>tnen diñley edik; <b>ребёнок с ~ем ел яблоко</b> bala almanı ist<stress>e</stress>knen aşay edi; <b>он работал с ~ем</b> (işinden) zevq alıp çalışa edi; <b>жить в своё ~е</b> zevq-sefa sürmek, yaşayışını zevq-sef<stress>a</stress>nen keçirmek",
            "accent_pos": null
        }
    ]
}