{
    "word": "отсутствие",
    "shortening_pos": 9,
    "articles": [
        {
            "text": "yoqluq, yoq oluv (<i>или</i> olm<stress>a</stress>),<stress>o</stress>lmayuv,<stress>o</stress>lmama, bul<stress>u</stress>nmayuv, bul<stress>u</stress>nmama; <i>также передаётся аффиксами</i> -sızlıq (-sizlik); <b>~е логики</b> mantıqnıñ yoqluğı, mantıqsızlıq; <b>~е желания</b> istegi<stress>o</stress>lmayuv (<i>или o</i>lmama), isteksizlik; <b>~е необходимости</b> kereksizlik; <b>~е цели</b> maqsatsızlıq; <b>~е главы семьи</b> qorantа başınıñ<stress>o</stress>lmaması; <b>при ~и этих условий</b> bu şartlar<stress>o</stress>lmağanda; <b>безвестное ~е</b> <i>юр.</i> habersiz bul<stress>u</stress>nmayuv (<i>или</i> bul<stress>u</stress>nmama); <b>за ~ем состава преступления</b> <i>юр.</i> cinayet faaliyeti<stress>o</stress>lmağanı içün; <b>в чьё-либо ~е</b> biri yoq olğanda",
            "accent_pos": null
        }
    ]
}