{
    "word": "оформить",
    "shortening_pos": 0,
    "articles": [
        {
            "text": "1. (<i>документ и т.п.</i>) resmiyleştirmek; <b>~ документы</b> vesıqalarını resmiyleştirmek; <b>~ договор</b> muqaveleni resmiyleştirmek (<i>или</i> resmiy tarzda tizmek); <b>~ на работу</b> işke (resmiy tarzda) almaq (<i>или</i> yerleştirmek); 2. süslemek; yaraştırmaq, bezetmek (<i>украсить</i>); donatmaq (<i>обставить, оборудовать</i>); resimlemek (<i>рисунками</i>); <b>~ стенд</b> stend süslemek; <b>~ книгу</b> kitapnı resimlemek",
            "accent_pos": null
        }
    ]
}