{
    "word": "передовой",
    "shortening_pos": 7,
    "articles": [
        {
            "text": "1. ögdeki, ögge ketken, ileri, ileride olğan; <b>~ой отряд</b> ögge ketken müfreze; <b>~ые позиции</b> ileri mevziler; 2. (<i>прогрессивный</i>) ileri, ileride olğan, ilerilegen, ilerilem<stress>e</stress>; <b>~ой опыт</b> ileri tecribe; <b>~ые взгляды</b> ilerilem<stress>e</stress> fikirler; <b>~ое человечество</b> ilerilegen insaniyet; <b>~ые страны</b> ileri (<i>или</i> ilerilegen) memleketler ◊<b>~ая статья</b> baş maqale",
            "accent_pos": null
        }
    ]
}