{
    "word": "процедура",
    "shortening_pos": 8,
    "articles": [
        {
            "text": "1. usul (<i>способ</i>); yol-yoruq (<i>последовательсность действий</i>); areket (<i>действие</i>); protsed<stress>u</stress>ra; <b>разъяснить ~у</b> yol-yoruğunı (<i>или</i> usulını) añlatmaq; <b>~а голосования</b> а) (<i>голосование</i>) rey berüv; б) (<i>способ голосования</i>) rey berüv usulı; <b>это – обычная юридическая ~а</b> bu, adiy bir uquqiy arek<stress>e</stress>ttir (<i>или</i> protsed<stress>u</stress>radır); 2. (<i>метод лечения</i>) tedaviy, protsed<stress>u</stress>ra; <b>водные ~ы</b> suv tedaviyi (<i>или</i> protseduraları); <b>ходить на ~ы</b> tedaviyge (<i>или</i> protseduralarğa) qatnamaq",
            "accent_pos": null
        }
    ]
}