{
    "word": "стрелка",
    "shortening_pos": 6,
    "articles": [
        {
            "text": "1. ine (<i>измерительного прибора, компаса</i>), til (<i>весов</i>), yelquvan (<i>минутная</i>), aqrep (<i>часовая</i>); 2. (<i>знак</i>) oq işareti, oq; <b>обозначить что-либо ~ой</b> bir şeyni<stress>o</stress>qnen (<i>или</i> oq işaret<stress>i</stress>nen) belgilemek; 3. (<i>на одежде</i>) cik; <b>~и брюк</b> ştannıñ cikleri; 4. (<i>ж.-д.</i>) maqas; <b>перевести ~у</b> maqasnı açmaq; 5. (<i>безлистый тонкий стебель лука, чеснока</i>) qıyaq",
            "accent_pos": null
        }
    ]
}