{
    "word": "съёмка",
    "shortening_pos": 5,
    "articles": [
        {
            "text": "1. (<i>фото-, теле-, кино-</i>) çekiş, çeküv, çekm<stress>e</stress>, çıqaruv, çıqarm<stress>a</stress>; çekilüv, çekilm<stress>e</stress>, çıqarıluv, çıqarılm<stress>a</stress>; <b>~и фильма</b> film çekişleri, filmni çeküv (<i>или</i> çekm<stress>e</stress>, çıqaruv, çıqarm<stress>a</stress>), filmniñ çekilüvi (<i>или</i> çekilmesi, çıqarıluvı, çıqarılması); <b>вести ~у</b> çekiş yapmaq; <b>натурные ~и</b> tış çekişler; <b>ночная ~а</b> gece çekişi; 2. (<i>измерение</i>) ölçev, ölçem<stress>e</stress>; <b>топографическая ~а</b> topograf<stress>i</stress>k ölçev",
            "accent_pos": null
        }
    ]
}