{
    "word": "вокруг",
    "shortening_pos": 0,
    "articles": [
        {
            "text": "1.<i>предлог</i> etraftа,<i>bir şeyniñ</i> etrafında; <b>~ дома</b> evniñ etrafında; <b>~ города</b> şeerniñ etrafında; 2.<i>нареч.</i> etrafında, çevresinde, çevre-çette, ortalıqtа; <b>~ никого нет</b> çevre-çette (bir) kimse yoq; <b>~ всё было тихо</b> ortalıq (<i>или</i> etraf) çım-çırt edi, etraftа ses-soluq yoq edi; <b>~ нас леса и озёра</b> etrafımızda ormanl<stress>a</stress>rnen göller bar; <b>оглянуться ~</b> etrafqa köz taşlamaq, etrafnı közden keçirmek",
            "accent_pos": null
        }
    ]
}