{
    "word": "и",
    "shortening_pos": null,
    "articles": [
        {
            "text": "<i>союз</i><b/>1. ve, ile, -nen, da, -ıp, -ip; <b>читать и писать</b> oqumaq ve yazmaq; <b>надо сидеть и ждать</b> oturıp (<i>или</i> oturıp turıp) beklemek kerek; <b>зимой и летом</b> yaz ve qış, yaz-qış; 2. em … em …; da, de; <b>и он, и ты</b> em о, em sen; <b>и другие</b> ve başqaları (<i>или</i> digerleri); <b>и тому подобное</b> ve il<stress>â</stress>hre, ve saire",
            "accent_pos": null
        },
        {
            "text": "<i>усил.</i> ne de, ne qadar da; <stress>a</stress>ttа, bile, da; <b>даже и тебя не позвал?</b> seni de (<i>или</i> bile) çağ<stress>ı</stress>rmadımı?; <b>мы зайдём и на рынок</b> bazarğa da kir<stress>e</stress>rmiz ◊<b>и вот</b> kel-kelelem; <b>и вот путешественники вернулись домой</b> kel-kelelem seyaatçılar evge qaytа (<i>или</i> qayttı); <b>и надо же</b> kel-kele, kelip-kelip; <b>и надо же беде со мной случиться</b> kelip-kelip belâ maña rastkeldi; <b>и только (и всё)</b> vesselâm, başqa bir şey ker<stress>e</stress>kmey; <b>от тебя требуется одно</b> :<b>учись хорошо и только</b> senden bir şey talap oluna: yahşı oqu - vesselâm",
            "accent_pos": null
        }
    ]
}