{
    "word": "защита",
    "shortening_pos": 5,
    "articles": [
        {
            "text": "1. (<i>охрана, поддержка</i>) imaye; <b>брать под ~у</b> imayesine almaq; 2. (<i>действие</i>) qoruv, qorum<stress>a</stress>, qorçalav, qorçalam<stress>a</stress>, imaye etüv (<i>или</i> etm<stress>e</stress>), mudafaа; <b>~а Родины</b> Vatannı imaye etüv, Vatannı qorçalav; <b>стоять на ~е интересов народа</b> halq menfaatını qorumaq; <b>~а диплома</b> diplom(nı) qorçalav; <b>~а от вирусов</b> viruslardan qorçalav; <b>~а персональных данных</b> şahsiy malümatnı qorçalav; 3.<i>юр.</i> (<i>сторона в судебном процессе</i>) mudafaa tarafı; <b>свидетели ~ы</b> mudafaa tarafınıñ şaatları; 4.<i>спорт.</i> mudafaа; <b>играть в ~е</b> mudafaа oynamaq; <b>уйти в ~у</b> mudafaağa çekilmek",
            "accent_pos": null
        }
    ]
}