{
    "word": "есть",
    "shortening_pos": 0,
    "articles": [
        {
            "text": "(<i>имеется</i>) bar; <b>у него ~ своя квартира</b> onıñ öz kvartirası bar; <b>у меня ~ пара вопросов</b> menim bir-eki sualim bar; <b>~ ли у вас такая деталь?</b> sizde böyle detal b<stress>a</stress>rmı? ◊<b>то ~</b> y<stress>a</stress>ni; <b>мы были там вчера, то ~ во вторник</b> biz anda t<stress>ü</stress>nevin, y<stress>a</stress>ni salı künü oldıq",
            "accent_pos": null
        },
        {
            "text": "1. (<i>кушать</i>) aşamaq; <b>~ть с аппетитом</b> iştа<stress>a</stress>nen (<i>или</i> madd<stress>e</stress>nen) aşamaq; <b>~ть с жадностью</b> açközl<stress>ü</stress>knen aşamaq, tıqınmaq; 2. (<i>мучить – о болезни, тоске</i>) kemirmek, hırpalamaq; 3. (<i>о дыме</i>) acıtmaq ◊<b>~ть поедом</b> ömrü-kününi aşamaq; <b>~т как скотина</b> ayvan (<i>или</i> domuz) kibi aşay",
            "accent_pos": null
        }
    ]
}