{
    "word": "язык",
    "shortening_pos": 0,
    "articles": [
        {
            "text": "1. til, lisan (<i>уст.</i>); <b>родной ~</b> ana tili, tuvğan til; <b>государственный ~</b> devlet tili; <b>~ жестов</b> jestler tili; <b>литературный ~</b> edebiy til; <b>искусственный ~</b> yapm<stress>a</stress> (<i>или</i> suniy) til; <b>~ обучения</b> oqutuv tili; <b>древние ~и</b> qadimiy tiller; <b>разговорный ~</b> laqırdı tili; <b>поэтический</b> şiiriy til; <b>газетный ~</b> gaz<stress>e</stress>tа tili; <b>~ программирования</b> programmalav tili; 2.<i>анат.</i> til; <b>налёт на ~е</b> til pası; <b>лизнуть ~ом</b> til<stress>i</stress>nen yalamaq; <b>показать ~</b> а) (eriştirip) tilini köstermek; б) (<i>доктору</i>) tilini köstermek; <b>у него отнялся ~</b> (onıñ) tili tutuldı; 3. (<i>военнопленный</i>) til, esir; 4. (<i>кушанье</i>) til ◊<b>~ музыки</b> m<stress>u</stress>zıka tili; <b>~и пламени</b> alevniñ yalınları; <b>не распускай ~</b> ,<b>держи ~ за зубами</b> tiliñni tut, yibere b<stress>e</stress>rme; <b>у него длинный ~</b> onıñ bir qarış tili bar; <b>у неё злой ~</b> biber kibi accı tili bar, tiline şeytan tükürgen; <b>у него ядовитый ~</b> onıñ tili zeerli; <b>он острый на ~</b> (onıñ) keskin tili bar; <b>развязать ~</b> tilini yibere bermek; <b>дать волю ~у</b> ağzını açmaq, ağzını açıp közüni yummaq; <b>у меня ~ не поворачивается сказать</b> aytmağa tilim b<stress>a</stress>rmay; <b>~ без костей</b> tilniñ kemigi yoq; <b>у меня ~ на плече</b> canım (<i>или</i> mırğam, pestilim) çıqtı; <b>у него ~ хорошо подвешен</b> laf ustası; laf etmege (pek yahşı) becere; laf etmege kâm<stress>i</stress>ldir; <b>держать ~</b> tilini tutmaq; <b>трепать (болтать) ~ом</b> tilini yibere bermek; <b>держи ~ за зубами</b> tiliñni tut; <b>~ мой – враг мой</b> bütün belâsı tilinden sebep; <b>типун тебе на ~!</b> ağzıñdan yel alsın!",
            "accent_pos": null
        }
    ]
}