{
    "word": "класть",
    "shortening_pos": 0,
    "articles": [
        {
            "text": "1. qoymaq, salmaq (<i>диал. ст.</i>); <b>чтобы не слиплись макароны, надо ~ их в кипящую воду</b> makaronlar bir-birine yap<stress>ı</stress>şmasın deseñ, qaynap turğan suv içine qoy<stress>a</stress>sıñ; <b>~ деньги в банк</b> paranı bankqa qoymaq; <b>~ деньги в карман</b> aqçanı cepke qoymaq; 2. (<i>добавлять</i>) qoymaq, qoşmaq; <b>~ сахар в кофе</b> qavege şeker qoymaq; 3. (<i>помещать</i>) yerleştirmek, qoymaq; yatqızmaq (<i>укладывать</i>); <b>~ в больницу</b> hastahanege yatqızmaq; 4. (<i>из кирпича, камня</i>) yapmaq; qalamaq; qurmaq (<i>строить</i>); çıqarmaq; <b>~ стену из ракушечника</b> qaburçaq taş<stress>ı</stress>nen divar qalamaq; <b>~ печь из кирпича</b> tol<stress>a</stress>nen soba yapmaq (<i>или</i> qalamaq); <b>~ дымоходную трубу</b> ocaq çıqarmaq",
            "accent_pos": null
        }
    ]
}